debug_sys/__init__.py
debug_sys/log_manager.py
debug_sys/logger.py
debug_sys-3.4.6.dist-info/LICENSE
debug_sys-3.4.6.dist-info/METADATA
debug_sys-3.4.6.dist-info/WHEEL
debug_sys-3.4.6.dist-info/top_level.txt
debug_sys-3.4.6.dist-info/RECORD
