Metadata-Version: 2.1
Name: debug_sys
Version: 3.4.6
Summary: A simple module to debug Python code
Home-page: https://github.com/Flyns157/debug_sys
Author: Cuisset Mattéo
Author-email: matteo.cuisset@gmail.com
Classifier: Programming Language :: Python :: 3
Classifier: License :: OSI Approved :: MIT License
Classifier: Operating System :: OS Independent
Requires-Python: >=3.12
License-File: LICENSE
